aws_recommendation_a13/__init__.py
aws_recommendation_a13/cloudwatch.py
aws_recommendation_a13/cost_estimations.py
aws_recommendation_a13/dynamodb.py
aws_recommendation_a13/ebs.py
aws_recommendation_a13/ec2.py
aws_recommendation_a13/elb.py
aws_recommendation_a13/kms.py
aws_recommendation_a13/rds.py
aws_recommendation_a13/recommendation.py
aws_recommendation_a13/redshift.py
aws_recommendation_a13/s3.py
aws_recommendation_a13/truted_advisor.py
aws_recommendation_a13/utils.py
aws_recommendation_a13-0.0.25.dist-info/LICENCE
aws_recommendation_a13-0.0.25.dist-info/METADATA
aws_recommendation_a13-0.0.25.dist-info/WHEEL
aws_recommendation_a13-0.0.25.dist-info/top_level.txt
aws_recommendation_a13-0.0.25.dist-info/RECORD
